<annotation>
	<folder>completas</folder>
	<filename>20250405_184401.jpg</filename>
	<path>D:\ProyectoDeGrado\proyecto-braille-final\datasets\libroCorazonDelator\completas\20250405_184401.jpg</path>
	<source>
		<database>Unknown</database>
	</source>
	<size>
		<width>6120</width>
		<height>8160</height>
		<depth>3</depth>
	</size>
	<segmented>0</segmented>
	<object>
		<name>M</name>
		<pose>Unspecified</pose>
		<truncated>0</truncated>
		<difficult>0</difficult>
		<bndbox>
			<xmin>360</xmin>
			<ymin>3296</ymin>
			<xmax>938</xmax>
			<ymax>4030</ymax>
		</bndbox>
	</object>
	<object>
		<name>A</name>
		<pose>Unspecified</pose>
		<truncated>0</truncated>
		<difficult>0</difficult>
		<bndbox>
			<xmin>958</xmin>
			<ymin>3297</ymin>
			<xmax>1327</xmax>
			<ymax>4038</ymax>
		</bndbox>
	</object>
	<object>
		<name>F</name>
		<pose>Unspecified</pose>
		<truncated>0</truncated>
		<difficult>0</difficult>
		<bndbox>
			<xmin>1878</xmin>
			<ymin>3521</ymin>
			<xmax>2382</xmax>
			<ymax>4307</ymax>
		</bndbox>
	</object>
	<object>
		<name>T</name>
		<pose>Unspecified</pose>
		<truncated>0</truncated>
		<difficult>0</difficult>
		<bndbox>
			<xmin>2458</xmin>
			<ymin>3262</ymin>
			<xmax>2982</xmax>
			<ymax>4041</ymax>
		</bndbox>
	</object>
	<object>
		<name>J</name>
		<pose>Unspecified</pose>
		<truncated>0</truncated>
		<difficult>0</difficult>
		<bndbox>
			<xmin>3582</xmin>
			<ymin>3489</ymin>
			<xmax>4086</xmax>
			<ymax>4262</ymax>
		</bndbox>
	</object>
	<object>
		<name>F</name>
		<pose>Unspecified</pose>
		<truncated>0</truncated>
		<difficult>0</difficult>
		<bndbox>
			<xmin>4747</xmin>
			<ymin>3503</ymin>
			<xmax>5237</xmax>
			<ymax>4197</ymax>
		</bndbox>
	</object>
	<object>
		<name>R</name>
		<pose>Unspecified</pose>
		<truncated>0</truncated>
		<difficult>0</difficult>
		<bndbox>
			<xmin>1285</xmin>
			<ymin>2348</ymin>
			<xmax>1799</xmax>
			<ymax>3086</ymax>
		</bndbox>
	</object>
	<object>
		<name>L</name>
		<pose>Unspecified</pose>
		<truncated>0</truncated>
		<difficult>0</difficult>
		<bndbox>
			<xmin>5268</xmin>
			<ymin>1452</ymin>
			<xmax>5696</xmax>
			<ymax>2076</ymax>
		</bndbox>
	</object>
</annotation>
